pylody/__init__.py
pylody/elements.py
pylody/parser.py
PyLody-1.0.0.dist-info/LICENSE
PyLody-1.0.0.dist-info/METADATA
PyLody-1.0.0.dist-info/WHEEL
PyLody-1.0.0.dist-info/top_level.txt
PyLody-1.0.0.dist-info/RECORD
