Metadata-Version: 2.1
Name: PyLody
Version: 1.0.0
Summary: A small package designed to create simple melodies
Home-page: UNKNOWN
Author: Gulg
Author-email: gulgdevs@yandex.com
License: UNKNOWN
Keywords: melody sound music
Platform: UNKNOWN
Classifier: Programming Language :: Python :: 3
Classifier: License :: OSI Approved :: MIT License
Classifier: Operating System :: Microsoft :: Windows
Classifier: Topic :: Multimedia :: Sound/Audio
Classifier: Programming Language :: Python :: 2
Classifier: Programming Language :: Python :: 2.7
Classifier: Programming Language :: Python :: 3
Classifier: Programming Language :: Python :: 3.6
Classifier: Programming Language :: Python :: 3.7
Classifier: Programming Language :: Python :: 3.8
Classifier: Programming Language :: Python :: 3.9
Classifier: Programming Language :: Python :: 3.10
Requires-Python: >=2.6, !=3.0.*, !=3.1.*, !=3.2.*
License-File: LICENSE
